realtime_pubsub_client/__init__.py
realtime_pubsub_client/client.py
realtime_pubsub_client/event_emitter.py
realtime_pubsub_client/wait_for.py
realtime_pubsub_client-1.0.0.dist-info/METADATA
realtime_pubsub_client-1.0.0.dist-info/WHEEL
realtime_pubsub_client-1.0.0.dist-info/licenses/LICENSE
realtime_pubsub_client-1.0.0.dist-info/RECORD
