Metadata-Version: 2.3
Name: realtime-pubsub-client
Version: 1.0.0
Summary: The official Realtime Pub/Sub client for Python
Author-email: Rolando Santamaria Maso <kyberneees@gmail.com>
License: MIT
License-File: LICENSE
Keywords: client,messaging,pubsub,python,realtime,websocket
Classifier: Framework :: AsyncIO
Classifier: Intended Audience :: Developers
Classifier: License :: OSI Approved :: MIT License
Classifier: Operating System :: OS Independent
Classifier: Programming Language :: Python :: 3
Classifier: Topic :: Communications
Classifier: Topic :: Internet
Classifier: Topic :: Software Development :: Libraries
Classifier: Topic :: System :: Networking
Requires-Python: >=3.6
Requires-Dist: websockets>=13.1
